colorizer_lite/__init__.py
colorizer_lite/colorizer.py
rz_color_lite-0.0.2.dist-info/METADATA
rz_color_lite-0.0.2.dist-info/WHEEL
rz_color_lite-0.0.2.dist-info/top_level.txt
rz_color_lite-0.0.2.dist-info/RECORD
